Workbook

Sheet COVER
H2: PEPSICO
F4: PepsiCo FP&A Annual Operating Plan
H5: Budgeting & Forecasting Model
I7: Historical Period: FY2020 - FY2025
I9: Forecast Period: FY2026 - FY2028
C11: Data Sources:
C13: • PepsiCo SEC 10-K filings
C14: • Annual Reports
C15: • Management Discussion & Annalysis
C24: Data Sources:
C26: • PepsiCo SEC 10-K Filings
C28: • Annual Reports
C30: • Management Discussion & Analysis

Sheet RAW_FINANCIALS
B2: Metric
D4: 20 | E4: 21 | F4: 22 | G4: 23 | H4: 24 | I4: 25
B6: Revenue | D6: 70372 | E6: 79474 | F6: 86392 | G6: 91471 | H6: 91854 | I6: 93925
B7: Cost of Sales | D7: 31797 | E7: 37075 | F7: 40576 | G7: 41881 | H7: 41744 | I7: 43066
B8: Gross Profit | D8: 38575 | E8: 42399 | F8: 45816 | G8: 49590 | H8: 50110 | I8: 50859
B9: SG&A | D9: 28495 | E9: 31237 | F9: 34459 | G9: 36677 | H9: 37190 | I9: 37368
B10: Operating Income | D10: 10080 | E10: 11162 | F10: 11512 | G10: 11986 | H10: 12887 | I10: 11498
B11: Operating Margin | D11: 0.1432 | E11: 0.14045 | F11: 0.13325 | G11: 0.13104 | H11: 0.1403 | I11: 0.12242
B12: Net Income | D12: 7120 | E12: 7618 | F12: 8910 | G12: 9074 | H12: 9578 | I12: 8240
B13: EPS | D13: 5.12 | E13: 5.49 | F13: 6.42 | G13: 6.56 | H13: 6.95 | I13: 6
B14: Diluted Shares Outstanding | D14: 1392 | E14: 1389 | F14: 1387 | G14: 1383 | H14: 1378 | I14: 1373
B15: Operating Cash Flow | D15: 10613 | E15: 11616 | F15: 10811 | G15: 13422 | H15: 12507 | I15: 12087
B16: Capital Expenditure | D16: 4240 | E16: 4625 | F16: 5207 | G16: 5518 | H16: 5318 | I16: 4415
B17: Free Cash Flow | D17: 6373 | E17: 6991 | F17: 5604 | G17: 7904 | H17: 7189 | I17: 7672
B18: Effective tax rate | D18: 20.9 | E18: 21.8 | F18: 16.1 | G18: 19.8 | H18: 19.4 | I18: 19
B21: Revenue growth % | D21: =D10/D6 -> 0.14323879 | E21: =E10/E6 -> 0.14044845 | F21: =F10/F6 -> 0.13325308 | G21: =G10/G6 -> 0.13103607 | H21: =H10/H6 -> 0.14029873 | I21: =I10/I6 -> 0.12241682
B22: COGS % revenue | D22: =D7/D6 -> 0.45184164 | E22: =E7/E6 -> 0.46650477 | F22: =F7/F6 -> 0.46967312 | G22: =G7/G6 -> 0.45786096 | H22: =H7/H6 -> 0.45446034 | I22: =I7/I6 -> 0.45851477
B23: SG&A % revenue | D23: =D9/D6 -> 0.40491957 | E23: =E9/E6 -> 0.39304678 | F23: =F9/F6 -> 0.39886795 | G23: =G9/G6 -> 0.40096861 | H23: =H9/H6 -> 0.40488166 | I23: =I9/I6 -> 0.39784935

Sheet HISTORICAL_KPIs
B2: KPI
D4: 2020 | E4: 2021 | F4: 2022 | G4: 2023 | H4: 2024 | I4: 2025
J5: average
B6: Revenue Growth % | E6: =(RAW_FINANCIALS!E6/RAW_FINANCIALS!D6)-1 -> 0.12934122 | F6: =(RAW_FINANCIALS!F6/RAW_FINANCIALS!E6)-1 -> 0.087047336 | G6: =(RAW_FINANCIALS!G6/RAW_FINANCIALS!F6)-1 -> 0.058790166 | H6: =(RAW_FINANCIALS!H6/RAW_FINANCIALS!G6)-1 -> 0.0041871194 | I6: =(RAW_FINANCIALS!I6/RAW_FINANCIALS!H6)-1 -> 0.02254665 | J6: =AVERAGE(E6:I6) -> 0.060382497
B7: Gross Margin % | E7: =RAW_FINANCIALS!E8/RAW_FINANCIALS!E6 -> 0.53349523 | F7: =RAW_FINANCIALS!F8/RAW_FINANCIALS!F6 -> 0.53032688 | G7: =RAW_FINANCIALS!G8/RAW_FINANCIALS!G6 -> 0.54213904 | H7: =RAW_FINANCIALS!H8/RAW_FINANCIALS!H6 -> 0.54553966 | I7: =RAW_FINANCIALS!I8/RAW_FINANCIALS!I6 -> 0.54148523 | J7: =AVERAGE(E7:I7) -> 0.53859721
B8: Operating Margin % | E8: =RAW_FINANCIALS!E10/RAW_FINANCIALS!E6 -> 0.14044845 | F8: =RAW_FINANCIALS!F10/RAW_FINANCIALS!F6 -> 0.13325308 | G8: =RAW_FINANCIALS!G10/RAW_FINANCIALS!G6 -> 0.13103607 | H8: =RAW_FINANCIALS!H10/RAW_FINANCIALS!H6 -> 0.14029873 | I8: =RAW_FINANCIALS!I10/RAW_FINANCIALS!I6 -> 0.12241682 | J8: =AVERAGE(E8:I8) -> 0.13349063
B9: SG&A % Revenue | E9: =RAW_FINANCIALS!E9/RAW_FINANCIALS!E6 -> 0.39304678 | F9: =RAW_FINANCIALS!F9/RAW_FINANCIALS!F6 -> 0.39886795 | G9: =RAW_FINANCIALS!G9/RAW_FINANCIALS!G6 -> 0.40096861 | H9: =RAW_FINANCIALS!H9/RAW_FINANCIALS!H6 -> 0.40488166 | I9: =RAW_FINANCIALS!I9/RAW_FINANCIALS!I6 -> 0.39784935 | J9: =AVERAGE(E9:I9) -> 0.39912287
B10: EPS Growth % | E10: =(RAW_FINANCIALS!E13/RAW_FINANCIALS!D13)-1 -> 0.072265625 | F10: =(RAW_FINANCIALS!F13/RAW_FINANCIALS!E13)-1 -> 0.16939891 | G10: =(RAW_FINANCIALS!G13/RAW_FINANCIALS!F13)-1 -> 0.021806854 | H10: =(RAW_FINANCIALS!H13/RAW_FINANCIALS!G13)-1 -> 0.05945122 | I10: =(RAW_FINANCIALS!I13/RAW_FINANCIALS!H13)-1 -> -0.13669065 | J10: =AVERAGE(E10:I10) -> 0.037246392
B11: Capex Growth % | E11: =(RAW_FINANCIALS!E16/RAW_FINANCIALS!D16)-1 -> 0.090801887 | F11: =(RAW_FINANCIALS!F16/RAW_FINANCIALS!E16)-1 -> 0.12583784 | G11: =(RAW_FINANCIALS!G16/RAW_FINANCIALS!F16)-1 -> 0.05972729 | H11: =(RAW_FINANCIALS!H16/RAW_FINANCIALS!G16)-1 -> -0.036245016 | I11: =(RAW_FINANCIALS!I16/RAW_FINANCIALS!H16)-1 -> -0.16980068 | J11: =AVERAGE(E11:I11) -> 0.014064264
B12: Capex revenue % | E12: =RAW_FINANCIALS!E16/RAW_FINANCIALS!E6 -> 0.058195133 | F12: =RAW_FINANCIALS!F16/RAW_FINANCIALS!F6 -> 0.060271784 | G12: =RAW_FINANCIALS!G16/RAW_FINANCIALS!G6 -> 0.06032513 | H12: =RAW_FINANCIALS!H16/RAW_FINANCIALS!H6 -> 0.057896227 | I12: =RAW_FINANCIALS!I16/RAW_FINANCIALS!I6 -> 0.04700559 | J12: =AVERAGE(E12:I12) -> 0.056738773
B13: Free Cash Flow Growth % | E13: =(RAW_FINANCIALS!E17/RAW_FINANCIALS!D17)-1 -> 0.096971599 | F13: =(RAW_FINANCIALS!F17/RAW_FINANCIALS!E17)-1 -> -0.19839794 | G13: =(RAW_FINANCIALS!G17/RAW_FINANCIALS!F17)-1 -> 0.41042113 | H13: =(RAW_FINANCIALS!H17/RAW_FINANCIALS!G17)-1 -> -0.090460526 | I13: =(RAW_FINANCIALS!I17/RAW_FINANCIALS!H17)-1 -> 0.067185979 | J13: =AVERAGE(E13:I13) -> 0.057144048

Sheet SEGMENT_REVENUE
B2: Segment
D4: FY20 | E4: FY21 | F4: FY22 | G4: FY23 | H4: FY24 | I4: FY25
B6: Frito-Lay North America | D6: 18189 | E6: 19608 | F6: 23291 | G6: 24914
B7: Quaker Foods North America | D7: 2742 | E7: 2751 | F7: 3160 | G7: 3101 | H7: 27431 | I7: 27528
B8: Pepsico Beverages North America | D8: 22559 | E8: 25276 | F8: 26213 | G8: 27626 | H8: 27769 | I8: 28197
B9: Latin America | D9: 6942 | E9: 8108 | F9: 9779 | G9: 11654 | H9: 10568 | I9: 10549
B10: Europe | D10: 11922 | E10: 13038 | F10: 12724 | G10: 13234 | H10: 4879 | I10: 4997
B11: Africa, Middle East & South Asia | D11: 4573 | E11: 6078 | F11: 6438 | G11: 6139 | H11: 16658 | I11: 18025
B12: Asia Pacific Australia & New Zealand China Region | D12: 3445 | E12: 4615 | F12: 4787 | G12: 4803 | H12: 4549 | I12: 4629
B14: Total Segment Revenue | D14: =SUM(D6:D12) -> 70372 | E14: =SUM(E6:E12) -> 79474 | F14: =SUM(F6:F12) -> 86392 | G14: =SUM(G6:G12) -> 91471 | H14: =SUM(H6:H12) -> 91854 | I14: =SUM(I6:I12) -> 93925
B15: Company Revenue | D15: =RAW_FINANCIALS!D6 -> 70372 | E15: =RAW_FINANCIALS!E6 -> 79474 | F15: =RAW_FINANCIALS!F6 -> 86392 | G15: =RAW_FINANCIALS!G6 -> 91471 | H15: =RAW_FINANCIALS!H6 -> 91854 | I15: =RAW_FINANCIALS!I6 -> 93925
B16: Difference | D16: =D14-D15 -> 0 | E16: =E14-E15 -> 0 | F16: =F14-F15 -> 0 | G16: =G14-G15 -> 0 | H16: =H14-H15 -> 0 | I16: =I14-I15 -> 0
D18: FY24-FY25 segments have been mapped to maintain consistency with historical reporting

Sheet MANAGEMENT_GUIDANCE
B2: Year | C2: Category | D2: Commentary | E2: Forecast Impact
B4: FY25 | C4: Revenue | D4: Effective net pricing became the primary driver | E4: Moderate revenue growth
B5: FY25 | C5: Revenue | D5: Organic volumes declined in North America | E5: Conservative volume assumptions
B6: FY25 | C6: Costs | D6: Commodity costs remained elevated | E6: Higher COGS
B7: FY25 | C7: Costs | D7: Tariffs increased input costs | E7: Margin pressure
B8: FY25 | C8: Margins | D8: Productivity savings offset inflation | E8: Stable operating margins
B9: FY24 | C9: Revenue | D9: Effective net pricing became the primary driver | E9: Moderate revenue growth
B10: FY24 | C10: Revenue | D10: Organic volumes declined in North America | E10: Conservative volume assumptions
B11: FY24 | C11: Costs | D11: Commodity costs remained elevated | E11: Higher COGS
B12: FY24 | C12: Margins | D12: Productivity savings offset cost pressures | E12: Stable margins
B13: FY24 | C13: Outlook | D13: Operating profit increased despite volume pressure | E13: Margins remain resilient

Sheet ASSUMPTIONS
B2: Drivers
D4: FY26 | E4: FY27 | F4: FY28
B6: Pricing Growth % | D6: 0.035 | E6: 0.03 | F6: 0.025
B7: Volume growth % | D7: 0.01 | E7: 0.015 | F7: 0.02
B8: Revenue Growth % | D8: 0.045 | E8: 0.045 | F8: 0.045
B9: Cost inflation % | D9: 0.03 | E9: 0.025 | F9: 0.02
B10: COGS % Revenue | D10: 0.4575 | E10: 0.455 | F10: 0.4525
B11: Gross Margin % | D11: 0.5425 | E11: 0.545 | F11: 0.5475
B12: SG&A % Revenue | D12: 0.4 | E12: 0.3975 | F12: 0.395
B13: Operating Margin % | D13: 0.125 | E13: 0.1275 | F13: 0.13
B14: Tax Rate | D14: 0.21 | E14: 0.21 | F14: 0.21
B15: Share Count Growth | D15: 0 | E15: 0 | F15: 0
B16: CapEX % Revenue | D16: 0.057 | E16: 0.057 | F16: 0.057
B18: Year | C18: Effective tax rate
B19: FY20 | C19: 20.9
B20: FY21 | C20: 21.8
B21: FY22 | C21: 16.1
B22: FY23 | C22: 19.8
B23: FY24 | C23: 19.4
B24: FY25 | C24: 19

Sheet FORECAST_MODEL
B2: Metric
D4: 20 | E4: 21 | F4: 22 | G4: 23 | H4: 24 | I4: 25 | J4: 26 | K4: 27 | L4: 28
B6: Revenue | D6: =RAW_FINANCIALS!D6 -> 70372 | E6: =RAW_FINANCIALS!E6 -> 79474 | F6: =RAW_FINANCIALS!F6 -> 86392 | G6: =RAW_FINANCIALS!G6 -> 91471 | H6: =RAW_FINANCIALS!H6 -> 91854 | I6: =RAW_FINANCIALS!I6 -> 93925 | J6: =I6*(1+ASSUMPTIONS!D8) -> 98151.625 | K6: =J6*(1+ASSUMPTIONS!E8) -> 102568.45 | L6: =K6*(1+ASSUMPTIONS!F8) -> 107184.03
B7: Revenue Growth % | E7: =(E6/D6)-1 -> 0.12934122 | F7: =(F6/E6)-1 -> 0.087047336 | G7: =(G6/F6)-1 -> 0.058790166 | H7: =(H6/G6)-1 -> 0.0041871194 | I7: =(I6/H6)-1 -> 0.02254665 | J7: =(J6/I6)-1 -> 0.045 | K7: =(K6/J6)-1 -> 0.045 | L7: =(L6/K6)-1 -> 0.045
B8: Cost of Sales | D8: =RAW_FINANCIALS!D7 -> 31797 | E8: =RAW_FINANCIALS!E7 -> 37075 | F8: =RAW_FINANCIALS!F7 -> 40576 | G8: =RAW_FINANCIALS!G7 -> 41881 | H8: =RAW_FINANCIALS!H7 -> 41744 | I8: =RAW_FINANCIALS!I7 -> 43066 | J8: =J6*ASSUMPTIONS!D10 -> 44904.368 | K8: =K6*ASSUMPTIONS!E10 -> 46668.644 | L8: =L6*ASSUMPTIONS!F10 -> 48500.773
B9: Gross Profit | D9: =RAW_FINANCIALS!D8 -> 38575 | E9: =RAW_FINANCIALS!E8 -> 42399 | F9: =RAW_FINANCIALS!F8 -> 45816 | G9: =RAW_FINANCIALS!G8 -> 49590 | H9: =RAW_FINANCIALS!H8 -> 50110 | I9: =RAW_FINANCIALS!I8 -> 50859 | J9: =J6-J8 -> 53247.257 | K9: =K6-K8 -> 55899.804 | L9: =L6-L8 -> 58683.255
B10: Gross Margin % | D10: =D9/D6 -> 0.54815836 | E10: =E9/E6 -> 0.53349523 | F10: =F9/F6 -> 0.53032688 | G10: =G9/G6 -> 0.54213904 | H10: =H9/H6 -> 0.54553966 | I10: =I9/I6 -> 0.54148523 | J10: =J9/J6 -> 0.5425 | K10: =K9/K6 -> 0.545 | L10: =L9/L6 -> 0.5475
B11: SG&A | D11: =RAW_FINANCIALS!D9 -> 28495 | E11: =RAW_FINANCIALS!E9 -> 31237 | F11: =RAW_FINANCIALS!F9 -> 34459 | G11: =RAW_FINANCIALS!G9 -> 36677 | H11: =RAW_FINANCIALS!H9 -> 37190 | I11: =RAW_FINANCIALS!I9 -> 37368 | J11: =J6*ASSUMPTIONS!D12 -> 39260.65 | K11: =K6*ASSUMPTIONS!E12 -> 40770.958 | L11: =L6*ASSUMPTIONS!F12 -> 42337.691
B12: SG&A % Revenue | D12: =D11/D6 -> 0.40491957 | E12: =E11/E6 -> 0.39304678 | F12: =F11/F6 -> 0.39886795 | G12: =G11/G6 -> 0.40096861 | H12: =H11/H6 -> 0.40488166 | I12: =I11/I6 -> 0.39784935 | J12: =J11/J6 -> 0.4 | K12: =K11/K6 -> 0.3975 | L12: =L11/L6 -> 0.395
B13: Operating Income | D13: =RAW_FINANCIALS!D10 -> 10080 | E13: =RAW_FINANCIALS!E10 -> 11162 | F13: =RAW_FINANCIALS!F10 -> 11512 | G13: =RAW_FINANCIALS!G10 -> 11986 | H13: =RAW_FINANCIALS!H10 -> 12887 | I13: =RAW_FINANCIALS!I10 -> 11498 | J13: =J9-J11 -> 13986.607 | K13: =K9-K11 -> 15128.846 | L13: =L9-L11 -> 16345.564
B14: Operating Margin % | D14: =RAW_FINANCIALS!D11 -> 0.1432 | E14: =RAW_FINANCIALS!E11 -> 0.14045 | F14: =RAW_FINANCIALS!F11 -> 0.13325 | G14: =RAW_FINANCIALS!G11 -> 0.13104 | H14: =RAW_FINANCIALS!H11 -> 0.1403 | I14: =I13/I6 -> 0.12241682 | J14: =J13/J6 -> 0.1425 | K14: =K13/K6 -> 0.1475 | L14: =L13/L6 -> 0.1525
B15: Net Income | D15: =RAW_FINANCIALS!D12 -> 7120 | E15: =RAW_FINANCIALS!E12 -> 7618 | F15: =RAW_FINANCIALS!F12 -> 8910 | G15: =RAW_FINANCIALS!G12 -> 9074 | H15: =RAW_FINANCIALS!H12 -> 9578 | I15: =RAW_FINANCIALS!I12 -> 8240 | J15: =J13*(1-ASSUMPTIONS!D14) -> 11049.419 | K15: =K13*(1-ASSUMPTIONS!E14) -> 11951.788 | L15: =L13*(1-ASSUMPTIONS!F14) -> 12912.996
B16: Tax Rate | D16: =RAW_FINANCIALS!D18 -> 20.9 | E16: =RAW_FINANCIALS!E18 -> 21.8 | F16: =RAW_FINANCIALS!F18 -> 16.1 | G16: =RAW_FINANCIALS!G18 -> 19.8 | H16: =RAW_FINANCIALS!H18 -> 19.4 | I16: =RAW_FINANCIALS!I18 -> 19 | J16: =ASSUMPTIONS!D14 -> 0.21 | K16: =ASSUMPTIONS!E14 -> 0.21 | L16: =ASSUMPTIONS!F14 -> 0.21
B17: Diluted Shares Outstanding | D17: 1392 | E17: 1389 | F17: 1387 | G17: 1383 | H17: 1378 | I17: 1373 | J17: =I17 -> 1373 | K17: =J17 -> 1373 | L17: =K17 -> 1373
B18: EPS | D18: =RAW_FINANCIALS!D13 -> 5.12 | E18: =RAW_FINANCIALS!E13 -> 5.49 | F18: =RAW_FINANCIALS!F13 -> 6.42 | G18: =RAW_FINANCIALS!G13 -> 6.56 | H18: =RAW_FINANCIALS!H13 -> 6.95 | I18: =RAW_FINANCIALS!I13 -> 6 | J18: =J15/J17 -> 8.0476469 | K18: =K15/K17 -> 8.7048714 | L18: =L15/L17 -> 9.4049496
B19: Operating Cashflow | D19: =RAW_FINANCIALS!D15 -> 10613 | E19: =RAW_FINANCIALS!E15 -> 11616 | F19: =RAW_FINANCIALS!F15 -> 10811 | G19: =RAW_FINANCIALS!G15 -> 13422 | H19: =RAW_FINANCIALS!H15 -> 12507 | I19: =RAW_FINANCIALS!I15 -> 12087 | J19: =I19*(1+J7) -> 12630.915 | K19: =J19*(1+K7) -> 13199.306 | L19: =K19*(1+L7) -> 13793.275
B20: Capital Expenditure | D20: =RAW_FINANCIALS!D16 -> 4240 | E20: =RAW_FINANCIALS!E16 -> 4625 | F20: =RAW_FINANCIALS!F16 -> 5207 | G20: =RAW_FINANCIALS!G16 -> 5518 | H20: =RAW_FINANCIALS!H16 -> 5318 | I20: =RAW_FINANCIALS!I16 -> 4415 | J20: =J6*HISTORICAL_KPIs!$J$12 -> 5569.0028 | K20: =K6*HISTORICAL_KPIs!$J$12 -> 5819.6079 | L20: =L6*HISTORICAL_KPIs!$J$12 -> 6081.4902
B21: CapEX % Revenue | D21: =D20/D6 -> 0.060251236 | E21: =E20/E6 -> 0.058195133 | F21: =F20/F6 -> 0.060271784 | G21: =G20/G6 -> 0.06032513 | H21: =H20/H6 -> 0.057896227 | I21: =I20/I6 -> 0.04700559 | J21: =J20/J6 -> 0.056738773 | K21: =K20/K6 -> 0.056738773 | L21: =L20/L6 -> 0.056738773
B22: Free Cash Flow | D22: =RAW_FINANCIALS!D17 -> 6373 | E22: =RAW_FINANCIALS!E17 -> 6991 | F22: =RAW_FINANCIALS!F17 -> 5604 | G22: =RAW_FINANCIALS!G17 -> 7904 | H22: =RAW_FINANCIALS!H17 -> 7189 | I22: =RAW_FINANCIALS!I17 -> 7672 | J22: =J19-J20 -> 7061.9122 | K22: =K19-K20 -> 7379.6983 | L22: =L19-L20 -> 7711.7847
B27: Notes:
B28: • Operating income forecast excludes non - recurring impairment and other operating expenses, representing normalized operating performance.
B29: • Revenue Forecast driven by pricing and volume assumptions.
B30: • Share count assumed flat through FY28.
B31: • CapEx forecast is based on historical average percentage of revenue.

Sheet FY26_AOP
B2: Metric
D4: 25 | E4: 26 | F4: Growth %
B6: Revenue | D6: =FORECAST_MODEL!I6 -> 93925 | E6: =FORECAST_MODEL!J6 -> 98151.625 | F6: =(E6/D6)-1 -> 0.045
B7: Cost of Sales | D7: =FORECAST_MODEL!I8 -> 43066 | E7: =FORECAST_MODEL!J8 -> 44904.368 | F7: =(E7/D7)-1 -> 0.042687234
B8: Gross Profit | D8: =FORECAST_MODEL!I9 -> 50859 | E8: =FORECAST_MODEL!J9 -> 53247.257 | F8: =(E8/D8)-1 -> 0.046958386
B9: Gross Margin % | D9: =FORECAST_MODEL!I10 -> 0.54148523 | E9: =FORECAST_MODEL!J10 -> 0.5425 | F9: =E9-D9 -> 0.0010147724
B10: SG&A | D10: =FORECAST_MODEL!I11 -> 37368 | E10: =FORECAST_MODEL!J11 -> 39260.65 | F10: =(E10/D10)-1 -> 0.050648951
B11: SG&A % Revenue | D11: =FORECAST_MODEL!I12 -> 0.39784935 | E11: =FORECAST_MODEL!J12 -> 0.4 | F11: =E11-D11 -> 0.0021506521
B12: Operating Income | D12: =FORECAST_MODEL!I13 -> 11498 | E12: =FORECAST_MODEL!J13 -> 13986.607 | F12: =(E12/D12)-1 -> 0.21643821
B13: Operating Margin % | D13: =FORECAST_MODEL!I14 -> 0.12241682 | E13: =FORECAST_MODEL!J14 -> 0.1425 | F13: =E13-D13 -> 0.020083178
B14: Net Income | D14: =FORECAST_MODEL!I15 -> 8240 | E14: =FORECAST_MODEL!J15 -> 11049.419 | F14: =(E14/D14)-1 -> 0.34094893
B15: EPS | D15: =FORECAST_MODEL!I18 -> 6 | E15: =FORECAST_MODEL!J18 -> 8.0476469 | F15: =(E15/D15)-1 -> 0.34127448
B16: Operating Cash Flow | D16: =FORECAST_MODEL!I19 -> 12087 | E16: =FORECAST_MODEL!J19 -> 12630.915 | F16: =(E16/D16)-1 -> 0.045
B17: Capital Expenditures | D17: =FORECAST_MODEL!I20 -> 4415 | E17: =FORECAST_MODEL!J20 -> 5569.0028 | F17: =(E17/D17)-1 -> 0.26138228
B18: Free Cash Flow | D18: =FORECAST_MODEL!I22 -> 7672 | E18: =FORECAST_MODEL!J22 -> 7061.9122 | F18: =(E18/D18)-1 -> -0.079521344

Sheet VARIANCE_ANALYSIS
B2: Metric
D4: 26 | E4: 26 | F4: Variance $ | G4: Variance % | H4: Commentary
B6: Revenue | D6: =FY26_AOP!E6 -> 98151.625 | E6: 97170 | F6: =E6-D6 -> -981.625 | G6: =(E6-D6)/D6 -> -0.010001108 | H6: Revenue missed budget due to softer consumer demand and lower unit volumes, partially offset by pricing actions.
B7: Cost of Sales | D7: =FY26_AOP!E7 -> 44904.368 | E7: 45920 | F7: =E7-D7 -> 1015.6316 | G7: =(E7-D7)/D7 -> 0.022617656 | H7: Commodity, packiging and freight costs remained elevated, resulting in higher than budget production expenses.
B8: Gross Profit | D8: =FY26_AOP!E8 -> 53247.257 | E8: =E6-E7 -> 51250 | F8: =E8-D8 -> -1997.2566 | G8: =(E8-D8)/D8 -> -0.037509098 | H8: Gross profit declined due to lower revenue and inflationary cost pressures that were not fully offset by pricing.
B9: Gross Margin % | D9: =FY26_AOP!E9 -> 0.5425 | E9: =E8/E6 -> 0.52742616 | G9: =E9-D9 -> -0.01507384 | H9: Gross margin contracted as cost inflation outpaced pricing and productivity initiatives.
B10: SG&A | D10: =FY26_AOP!E10 -> 39260.65 | E10: 39650 | F10: =E10-D10 -> 389.35 | G10: =(E10-D10)/D10 -> 0.0099170544 | H10: SG&A exceeded budget due to higher adversting, promotional spending and investment in digital initiatives.
B11: Operating Income | D11: =FY26_AOP!E12 -> 13986.607 | E11: =E8-E10 -> 11600 | F11: =E11-D11 -> -2386.6066 | G11: =(E11-D11)/D11 -> -0.17063514 | H11: Operating income declined as lower gross profit and higher SG&A expenses compressed profitablility.
B12: Operating Margin % | D12: =FY26_AOP!E13 -> 0.1425 | E12: =E11/E6 -> 0.11937841 | G12: =E12-D12 -> -0.023121591 | H12: Operating margin fell below budget driven by weaker sales and inflationary cost pressures.
B13: Net Income | D13: =FY26_AOP!E14 -> 11049.419 | E13: =E11*(1-21%) -> 9164 | F13: =E13-D13 -> -1885.4192 | G13: =(E13-D13)/D13 -> -0.17063514 | H13: Net income declined inline with lower operating income and reduced profitability.
B14: EPS | D14: =FY26_AOP!E15 -> 8.0476469 | E14: =E13/FORECAST_MODEL!J17 -> 6.6744355 | F14: =E14-D14 -> -1.3732114 | G14: =(E14-D14)/D14 -> -0.17063514 | H14: EPS was below budget primarily due to lower earnings performance during the year.
B15: Operating Cashflow | D15: =FY26_AOP!E16 -> 12630.915 | E15: 12100 | F15: =E15-D15 -> -530.915 | G15: =(E15-D15)/D15 -> -0.04203298 | H15: Operating cashflow was lower than budget due to weaker earnings and higher working capital requirements.
B16: Capital Expenditure | D16: =FY26_AOP!E17 -> 5569.0028 | E16: 5500 | F16: =E16-D16 -> -69.00275 | G16: =(E16-D16)/D16 -> -0.012390504 | H16: Capital spending came in below budget as certain manufacturing and productivity projects were deferred.
B17: Free Cash Flow | D17: =FY26_AOP!E18 -> 7061.9122 | E17: =E15-E16 -> 6600 | F17: =E17-D17 -> -461.91225 | G17: =(E17-D17)/D17 -> -0.065408948 | H17: Free cashflow declined as lower operating cashflow more than offset reduced capital spending.

Sheet SCENARIO_ANALYSIS
B2: Assumptions | I2: Selected scenario
I3: Base
D4: Downside | E4: Base | F4: Upside
I5: Active assumptions | K5: Value
B6: Revenue Growth % | D6: 0.025 | E6: =ASSUMPTIONS!D8 -> 0.045 | F6: 0.06
B7: Pricing Growth % | D7: 0.02 | E7: =ASSUMPTIONS!D6 -> 0.035 | F7: 0.04 | I7: Revenue Growth % | K7: =_xlfn.XLOOKUP($I$3,$D$4:$F$4,D6:F6) -> 0.045
B8: Volume Growth % | D8: 0.005 | E8: =ASSUMPTIONS!D7 -> 0.01 | F8: 0.02 | I8: Pricing Growth % | K8: =_xlfn.XLOOKUP($I$3,$D$4:$F$4,D7:F7) -> 0.035
B9: Cost Inflation % | D9: 0.04 | E9: =ASSUMPTIONS!D9 -> 0.03 | F9: 0.02 | I9: Volume Growth % | K9: =_xlfn.XLOOKUP($I$3,$D$4:$F$4,D8:F8) -> 0.01
B10: COGS % Revenue | D10: 0.465 | E10: =ASSUMPTIONS!D10 -> 0.4575 | F10: 0.45 | I10: Cost Inflation % | K10: =_xlfn.XLOOKUP($I$3,$D$4:$F$4,D9:F9) -> 0.03
B11: SG&A % Revenue | D11: 0.405 | E11: =ASSUMPTIONS!D12 -> 0.4 | F11: 0.395 | I11: COGS % Revenue | K11: =_xlfn.XLOOKUP($I$3,$D$4:$F$4,D10:F10) -> 0.4575
I12: SG&A % Revenue | K12: =_xlfn.XLOOKUP($I$3,$D$4:$F$4,D11:F11) -> 0.4
I15: Output Metrics
I17: Revenue | K17: =FORECAST_MODEL!I6*(1+SCENARIO_ANALYSIS!K7) -> 98151.625
I18: Cost of sales | K18: =K17*K11 -> 44904.368
I19: Gross Profit | K19: =K17-K18 -> 53247.257
I20: SG&A | K20: =K17*K12 -> 39260.65
I21: Operating Income | K21: =K19-K20 -> 13986.607
I22: Operating Margin | K22: =K21/K17 -> 0.1425
I23: Net Income | K23: =K21*(1-FORECAST_MODEL!J16) -> 11049.419
I24: EPS | K24: =K23/FORECAST_MODEL!J17 -> 8.0476469
I25: Operating Cashflow | K25: =FORECAST_MODEL!I19*(1+SCENARIO_ANALYSIS!K7) -> 12630.915
I26: CapEx | K26: =K17*FORECAST_MODEL!J21 -> 5569.0028
I27: Free Cash Flow | K27: =K25-K26 -> 7061.9122

Sheet KPI_DASHBOARD
B1: PEPSICO FP&A DASHBOARD FY26 ANNUAL OPERATING PLAN
B3: HISTORICAL PERFORMANCE (FY20 - FY25) AND FY26-FY28 FORECAST
AA4: YEAR | AB4: GROSS MARGIN % | AC4: OPERATING MARGIN %
B5: REVENUE | G5: REVENUE GROWTH | L5: GROSS MARGIN % | AA5: 20 | AB5: =FORECAST_MODEL!D10 -> 0.54815836 | AC5: =FORECAST_MODEL!D14 -> 0.1432
AA6: 21 | AB6: =FORECAST_MODEL!E10 -> 0.53349523 | AC6: =FORECAST_MODEL!E14 -> 0.14045
B7: =FORECAST_MODEL!J6 -> 98151.625 | G7: =FORECAST_MODEL!J7 -> 0.045 | L7: =FORECAST_MODEL!J10 -> 0.5425 | AA7: 22 | AB7: =FORECAST_MODEL!F10 -> 0.53032688 | AC7: =FORECAST_MODEL!F14 -> 0.13325
AA8: 23 | AB8: =FORECAST_MODEL!G10 -> 0.54213904 | AC8: =FORECAST_MODEL!G14 -> 0.13104
AA9: 24 | AB9: =FORECAST_MODEL!H10 -> 0.54553966 | AC9: =FORECAST_MODEL!H14 -> 0.1403
AA10: 25 | AB10: =FORECAST_MODEL!I10 -> 0.54148523 | AC10: =FORECAST_MODEL!I14 -> 0.12241682
AA11: 26 | AB11: =FORECAST_MODEL!J10 -> 0.5425 | AC11: =FORECAST_MODEL!J14 -> 0.1425
AA12: 27 | AB12: =FORECAST_MODEL!K10 -> 0.545 | AC12: =FORECAST_MODEL!K14 -> 0.1475
B13: OPERATING MARGIN % | G13: EPS | L13: FREE CASH FLOW | AA13: 28 | AB13: =FORECAST_MODEL!L10 -> 0.5475 | AC13: =FORECAST_MODEL!L14 -> 0.1525
B15: =FORECAST_MODEL!J14 -> 0.1425 | G15: =FORECAST_MODEL!J18 -> 8.0476469 | L15: =FORECAST_MODEL!J22 -> 7061.9122

Sheet MANAGEMENT_RECOMMENDATIONS
B2: Priority | C2: Observation | D2: Business Impact | E2: Recommendation | F2: Estimated Financial Impact | G2: Owner
B3: High | C3: Pricing has been the primary driver for revenue growth whereas uit volume growth has been weak across recent periods. | D3: Reliance on price increases may limit long term revenue growth if consumers end up shifting toward lower priced alternatives. | E3: Increase focus on volume led growth through product innovation, targeted promotions, and expansion of high growth product categories while maintaining disciplined pricing strategies. | F3: A 1% improvemnet in annual volume growth could increase revenue by approximately $0.9 - 1.0 billion based on the FY26 revenue forecast. | G3: Commercial Finance/ Sales.
B4: High | C4: Cost of Sales and SG&A remianed elevated relative to budget, reducing operating profitability despite revenue growth. | D4: Higher operating costs compress margins and reduce earnings and free cash flow available for reinvestment. | E4: Contnue productivity initiatives, strengthen procurement efficiency and optimize SG&A spending while procteting strategic growth invetsments. | F4: A 0.5 percentage point reduction in COGS could improve annual operating income by approximately $490 million based on the FY26 revenue forecast. | G4: Supply Chain/ Procuremnt/ Finance
B5: Medium | C5: Free cash flwo has remianed positive but varies with changes in operating cash flwo and capital expenditures. | D5: Strong and consistent free cash flow provides greater flexibility for capital investments, dividends, share repurchases, and debt reduction. | E5: Prioritze high return capital projects and continuously evaluate capital spending to maximize long term shareholder value while maintaining healthy cash generation. | F5: A 5% improvement in operating cash flow would increase annual free cash flow by approximately $600 million, assuming capital spending remians constant. | G5: Finance/ Treasury/ Capital Planning
B6: Medium | C6: Budget to actual variances indicate that several planning assumptions differed from actual business performance. | D6: Forecast inaccuracies may delay management decisions and reduce the effectiveness of financial planning. | E6: Enhance rolling forecasts by incorporating monthly variance reviews and updated business assumptions to improve forecast accuracy. | F6: Improved forecast accuracy can support timely resource allocation and reduce unexpected budget variances across business units. | G6: FP&A
B7: Low | C7: Business performace remians sensitive to inflation, foreign exchange movements, commodity costs, and changes in consumer demand. | D7: External market conditions may significantly affect revenue growth, operaing margins and profitability. | E7: Continue using scenario analysis during the planning process to evaluate potential risks and prepare contingency plans for changing market conditions. | F7: Proactive scenario planning supports faster decision making and helps protect profitability inder changing economic conditions. | G7: FP&A/ Executive Leadership
